pytorch_tabnet/__init__.py
pytorch_tabnet/callbacks/__init__.py
pytorch_tabnet/callbacks/callback.py
pytorch_tabnet/callbacks/container.py
pytorch_tabnet/callbacks/early_stopping.py
pytorch_tabnet/callbacks/history.py
pytorch_tabnet/callbacks/lr_scheduler.py
pytorch_tabnet/data_handlers/__init__.py
pytorch_tabnet/data_handlers/data_handler_funcs.py
pytorch_tabnet/data_handlers/data_types.py
pytorch_tabnet/data_handlers/tb_dataloader.py
pytorch_tabnet/data_handlers/unified_dataset.py
pytorch_tabnet/error_handlers/__init__.py
pytorch_tabnet/error_handlers/_assert_all_finite.py
pytorch_tabnet/error_handlers/data.py
pytorch_tabnet/error_handlers/embedding_errors.py
pytorch_tabnet/error_handlers/validation.py
pytorch_tabnet/metrics/__init__.py
pytorch_tabnet/metrics/accuracy.py
pytorch_tabnet/metrics/auc.py
pytorch_tabnet/metrics/balanced_accuracy.py
pytorch_tabnet/metrics/base_metrics.py
pytorch_tabnet/metrics/logloss.py
pytorch_tabnet/metrics/mae.py
pytorch_tabnet/metrics/mse.py
pytorch_tabnet/metrics/rmse.py
pytorch_tabnet/metrics/rmsle.py
pytorch_tabnet/metrics/unsupervised_loss.py
pytorch_tabnet/metrics/unsupervised_metrics.py
pytorch_tabnet/tab_models/__init__.py
pytorch_tabnet/tab_models/multitask.py
pytorch_tabnet/tab_models/pretraining.py
pytorch_tabnet/tab_models/tab_class.py
pytorch_tabnet/tab_models/tab_reg.py
pytorch_tabnet/tab_models/abstract_models/__init__.py
pytorch_tabnet/tab_models/abstract_models/abs_model.py
pytorch_tabnet/tab_models/abstract_models/base_model.py
pytorch_tabnet/tab_models/abstract_models/base_supervised_model.py
pytorch_tabnet/tab_models/abstract_models/supervised_model.py
pytorch_tabnet/tab_network/__init__.py
pytorch_tabnet/tab_network/attentive_transformer.py
pytorch_tabnet/tab_network/embedding_generator.py
pytorch_tabnet/tab_network/feat_transformer.py
pytorch_tabnet/tab_network/gbn.py
pytorch_tabnet/tab_network/glu_block.py
pytorch_tabnet/tab_network/glu_layer.py
pytorch_tabnet/tab_network/random_obfuscator.py
pytorch_tabnet2-4.5.4.dist-info/METADATA
pytorch_tabnet2-4.5.4.dist-info/WHEEL
pytorch_tabnet2-4.5.4.dist-info/licenses/LICENSE
pytorch_tabnet2-4.5.4.dist-info/RECORD
