Metadata-Version: 2.4
Name: pytorch-tabnet2
Version: 4.5.4
Summary: PyTorch implementation of TabNet
Author: DreamQuark
Author-email: DanielAvdar <66269169+DanielAvdar@users.noreply.github.com>
License-File: LICENSE
Keywords: neural-networks,pytorch,tabnet
Classifier: Intended Audience :: Developers
Classifier: Intended Audience :: Science/Research
Classifier: License :: OSI Approved :: MIT License
Classifier: Operating System :: OS Independent
Classifier: Programming Language :: Python :: 3
Classifier: Programming Language :: Python :: 3.10
Classifier: Programming Language :: Python :: 3.11
Classifier: Programming Language :: Python :: 3.12
Classifier: Programming Language :: Python :: 3.13
Classifier: Programming Language :: Python :: 3.14
Classifier: Topic :: Scientific/Engineering :: Artificial Intelligence
Requires-Python: >=3.10
Requires-Dist: activations-plus>=0.1.1
Requires-Dist: numpy
Requires-Dist: scikit-learn
Requires-Dist: torch; python_version < '3.13'
Requires-Dist: torch>=2.6; python_version >= '3.13'
Requires-Dist: torcheval
